getting/__init__.py
getting/audio.py
getting/auth.py
getting/database/__init__.py
getting/database/config.py
getting/django/__init__.py
getting/django/config.py
getting/encrypt.py
getting/file.py
getting/gamecreator/__init__.py
getting/gamecreator/auth.py
getting/gamecreator/plug_cover.py
getting/gitea/__init__.py
getting/gitea/apiobject.py
getting/gitea/baseapiobject.py
getting/gitea/exceptions.py
getting/gitea/gitea.py
getting/json.py
getting/proxy.py
getting/pymysql/__init__.py
getting/pymysql/sql.py
getting/response.py
getting-1.4.0.dist-info/METADATA
getting-1.4.0.dist-info/WHEEL
getting-1.4.0.dist-info/RECORD
