Metadata-Version: 2.3
Name: getting
Version: 1.4.0
Summary: 操作检查各种操作
Home-page: https://github.com/BlackWhite2000/Getting
Author: BlackWhite
Author-email: jierong8215@gmail.com
Requires-Python: >=3.10,<4.0
Classifier: Programming Language :: Python :: 3
Classifier: Programming Language :: Python :: 3.10
Classifier: Programming Language :: Python :: 3.11
Classifier: Programming Language :: Python :: 3.12
Classifier: Programming Language :: Python :: 3.13
Requires-Dist: django (>=5.0,<6.0)
Requires-Dist: eyed3 (>=0.9.7,<0.10.0)
Requires-Dist: loguru (==0.7.3)
Requires-Dist: mutagen (>=1.47.0,<2.0.0)
Requires-Dist: pillow (>=10.1.0,<11.0.0)
Requires-Dist: psutil (>=5.9.6,<6.0.0)
Requires-Dist: pycryptodome (>=3.20.0,<4.0.0)
Requires-Dist: pyjwt (>=2.8.0,<3.0.0)
Requires-Dist: pymysql (>=1.1.0,<2.0.0)
Requires-Dist: python-decouple (>=3.8,<4.0)
Requires-Dist: requests (>=2.31.0,<3.0.0)
Requires-Dist: rsa (>=4.9,<5.0)
Requires-Dist: tqdm (>=4.66.1,<5.0.0)
Project-URL: Repository, https://github.com/BlackWhite2000/Getting
